bound_propagation/__init__.py
bound_propagation/activation.py
bound_propagation/bivariate.py
bound_propagation/bounds.py
bound_propagation/factory.py
bound_propagation/general.py
bound_propagation/linear.py
bound_propagation/parallel.py
bound_propagation/polynomial.py
bound_propagation/probability.py
bound_propagation/reshape.py
bound_propagation/saturation.py
bound_propagation/sequential.py
bound_propagation/util.py
bound_propagation-0.4.6.dist-info/licenses/LICENSE
bound_propagation-0.4.6.dist-info/METADATA
bound_propagation-0.4.6.dist-info/WHEEL
bound_propagation-0.4.6.dist-info/top_level.txt
bound_propagation-0.4.6.dist-info/RECORD
