Metadata-Version: 2.4
Name: bound_propagation
Version: 0.4.6
Summary: Bound propagation in Pytorch
Home-page: https://github.com/zinoex/bound_propagation
Author: Frederik Baymler Mathiesen
Author-email: frederik@baymler.com
Project-URL: Bug Tracker, https://github.com/zinoex/bound_propagation/issues
Classifier: Programming Language :: Python :: 3
Classifier: License :: OSI Approved :: GNU General Public License v3 (GPLv3)
Classifier: Operating System :: OS Independent
Requires-Python: >=3.6
License-File: LICENSE
Requires-Dist: torch
Requires-Dist: numpy
Dynamic: author
Dynamic: author-email
Dynamic: classifier
Dynamic: description
Dynamic: description-content-type
Dynamic: home-page
Dynamic: license-file
Dynamic: project-url
Dynamic: requires-dist
Dynamic: requires-python
Dynamic: summary
